Adhesion/ChangeLog.md
Adhesion/DiscoverVersion.py
Adhesion/__init__.py
Adhesion/CommandLineInterface/SoftWall.py
Adhesion/CommandLineInterface/__init__.py
Adhesion/Interactions/Base.py
Adhesion/Interactions/Coulomb.py
Adhesion/Interactions/Cutoff.py
Adhesion/Interactions/Exponential.py
Adhesion/Interactions/Harmonic.py
Adhesion/Interactions/LJ93.py
Adhesion/Interactions/Potential.py
Adhesion/Interactions/PowerLaw.py
Adhesion/Interactions/SmoothPotential.py
Adhesion/Interactions/VdW82.py
Adhesion/Interactions/__init__.py
Adhesion/ReferenceSolutions/BaneyHui.py
Adhesion/ReferenceSolutions/DMT.py
Adhesion/ReferenceSolutions/JKR.py
Adhesion/ReferenceSolutions/MaugisDugdale.py
Adhesion/ReferenceSolutions/PastewkaRobbins.py
Adhesion/ReferenceSolutions/__init__.py
Adhesion/ReferenceSolutions/sinewave/JKR.py
Adhesion/ReferenceSolutions/sinewave/__init__.py
Adhesion/System/Factory.py
Adhesion/System/PlasticSystemSpecialisations.py
Adhesion/System/SmoothSystemSpecialisations.py
Adhesion/System/Systems.py
Adhesion/System/__init__.py
adhesion-0.92.1.dist-info/entry_points.txt
adhesion-0.92.1.dist-info/licenses/LICENSE.md
adhesion-0.92.1.dist-info/WHEEL
adhesion-0.92.1.dist-info/METADATA
adhesion-0.92.1.dist-info/RECORD
