Metadata-Version: 2.4
Name: Adhesion
Version: 0.92.1
Summary: Surface forces in contact calculations
Author-email: Till Junge <till.junge@altermail.ch>, Antoine Sanner <asanner@ethz.ch>, Lars Pastewka <lars.pastewka@imtek.uni-freiburg.de>
Requires-Python: >=3.8.0
Classifier: Development Status :: 5 - Production/Stable
Classifier: Programming Language :: Python
License-File: LICENSE.md
Requires-Dist: DiscoverVersion
Requires-Dist: numpy
Requires-Dist: scipy>=1.9.0
Requires-Dist: NuMPI>=0.5.0
Requires-Dist: muFFT>=0.93.1
Requires-Dist: SurfaceTopography>=1.18.3
Requires-Dist: ContactMechanics>=1.6.0
Requires-Dist: netCDF4
Requires-Dist: sphinx ; extra == "docs"
Requires-Dist: sphinx-rtd-theme ; extra == "docs"
Requires-Dist: myst_nb ; extra == "docs"
Requires-Dist: numpydoc ; extra == "docs"
Requires-Dist: jupytext ; extra == "docs"
Requires-Dist: flake8<8 ; extra == "test"
Requires-Dist: pytest ; extra == "test"
Requires-Dist: pytest-cov ; extra == "test"
Requires-Dist: pytest-flake8 ; extra == "test"
Requires-Dist: runtests ; extra == "test"
Project-URL: changelog, https://github.com/ContactEngineering/Adhesion/blob/master/Adhesion/ChangeLog.md
Project-URL: documentation, https://contactengineering.github.io/Adhesion/
Project-URL: repository, https://github.com/ContactEngineering/Adhesion
Provides-Extra: docs
Provides-Extra: test
